bankreader/__init__.py
bankreader/romania/__init__.py
bankreader/romania/raiffeisen.py
bankreader-0.2.3.dist-info/LICENSE
bankreader-0.2.3.dist-info/METADATA
bankreader-0.2.3.dist-info/WHEEL
bankreader-0.2.3.dist-info/top_level.txt
bankreader-0.2.3.dist-info/RECORD
