Metadata-Version: 2.1
Name: bankreader
Version: 0.2.3
Summary: Romanian banks statement parser
Home-page: https://github.com/abarbatei/bankreader
Author: Alin BARBATEI
License: MIT
Download-URL: https://github.com/abarbatei/bankreader/archive/0.2.2.tar.gz
Platform: UNKNOWN
Classifier: Development Status :: 4 - Beta
Classifier: Programming Language :: Python :: 3
Classifier: License :: OSI Approved :: MIT License
Classifier: Operating System :: OS Independent
Requires-Dist: pandas (>=0.23.4)
